Metadata-Version: 2.1
Name: utspclient
Version: 0.2.1
Summary: Universal Time Series Provider Client
Home-page: https://github.com/FZJ-IEK3-VSA/UTSP_Client
Author: David Neuroth
Author-email: d.neuroth@fz-juelich.de
License: MIT license
Keywords: time series,load profile,thermal load,electricity load
Classifier: Development Status :: 3 - Alpha
Classifier: Intended Audience :: End Users/Desktop
Classifier: Intended Audience :: Science/Research
Classifier: License :: OSI Approved :: MIT License
Classifier: Natural Language :: English
Classifier: Operating System :: OS Independent
Classifier: Programming Language :: Python
Classifier: Programming Language :: Python :: 3
Classifier: Programming Language :: Python :: 3.11
Classifier: Topic :: Scientific/Engineering
Classifier: Topic :: Software Development :: Libraries :: Python Modules
License-File: LICENSE
Requires-Dist: setuptools
Requires-Dist: requests
Requires-Dist: dataclasses-json
Requires-Dist: tqdm
Requires-Dist: sphinx-rtd-theme
